service_forge/__init__.py
service_forge/current_service.py
service_forge/service.py
service_forge/service_config.py
service_forge/api/http_api.py
service_forge/api/http_api_doc.py
service_forge/api/kafka_api.py
service_forge/api/service_studio.py
service_forge/api/routers/feedback/feedback_router.py
service_forge/api/routers/meta_api/meta_api_router.py
service_forge/api/routers/service/service_router.py
service_forge/api/routers/trace/trace_router.py
service_forge/api/routers/websocket/websocket_manager.py
service_forge/api/routers/websocket/websocket_router.py
service_forge/db/__init__.py
service_forge/db/database.py
service_forge/db/trace_mixin.py
service_forge/db/migrations/feedback_migration.py
service_forge/db/models/__init__.py
service_forge/db/models/feedback.py
service_forge/frontend/static/index.html
service_forge/frontend/static/assets/EditorSidePanel-BLIPel8z.js
service_forge/frontend/static/assets/EditorSidePanel-BNVms9Fq.css
service_forge/frontend/static/assets/FeedbackPanel-CUndA78i.css
service_forge/frontend/static/assets/FeedbackPanel-DufEqQxi.js
service_forge/frontend/static/assets/FloatPagination-C3Q9DXfH.css
service_forge/frontend/static/assets/FloatPagination-x9oqNWsY.js
service_forge/frontend/static/assets/FormattedCodeViewer.vue_vue_type_script_setup_true_lang-D-r0d4Is.js
service_forge/frontend/static/assets/NodeDetailWrapper-KfsWKrNS.css
service_forge/frontend/static/assets/NodeDetailWrapper-tuRfvIsa.js
service_forge/frontend/static/assets/TracePanelWrapper-BLAMynpF.css
service_forge/frontend/static/assets/TracePanelWrapper-CGsS47oK.js
service_forge/frontend/static/assets/WorkflowEditor-D8-6OZ8Y.js
service_forge/frontend/static/assets/WorkflowEditor-DMina2Ac.css
service_forge/frontend/static/assets/WorkflowList-B-B_BNi1.js
service_forge/frontend/static/assets/WorkflowList-Copuwi-a.css
service_forge/frontend/static/assets/WorkflowStudio-B8WFoV8O.css
service_forge/frontend/static/assets/WorkflowStudio-cipvlP3c.js
service_forge-0.1.66.dist-info/METADATA
service_forge-0.1.66.dist-info/WHEEL
service_forge-0.1.66.dist-info/entry_points.txt
service_forge-0.1.66.dist-info/RECORD
