Metadata-Version: 2.4
Name: service-forge
Version: 0.1.66
Summary: Add your description here
Author-email: euxcet <zcc.qwer@gmail.com>
Requires-Python: >=3.11
Requires-Dist: a2a-sdk>=0.3.22
Requires-Dist: aiokafka>=0.12.0
Requires-Dist: alembic>=1.17.0
Requires-Dist: asyncpg>=0.30.0
Requires-Dist: dotenv>=0.9.9
Requires-Dist: fastapi>=0.119.1
Requires-Dist: greenlet>=3.2.4
Requires-Dist: jinja2>=3.1.6
Requires-Dist: kubernetes>=28.0.0
Requires-Dist: litellm>=1.81.0
Requires-Dist: loguru>=0.7.3
Requires-Dist: omegaconf>=2.3.0
Requires-Dist: openai>=2.3.0
Requires-Dist: opentelemetry-api>=1.38.0
Requires-Dist: opentelemetry-exporter-otlp>=1.38.0
Requires-Dist: opentelemetry-instrumentation-asgi>=0.60b1
Requires-Dist: opentelemetry-instrumentation-fastapi>=0.60b1
Requires-Dist: opentelemetry-sdk>=1.38.0
Requires-Dist: protobuf>=6.33.1
Requires-Dist: psycopg2-binary>=2.9.11
Requires-Dist: pydantic>=2.12.0
Requires-Dist: pymongo>=4.15.5
Requires-Dist: pytest-asyncio>=1.2.0
Requires-Dist: pytest>=8.4.2
Requires-Dist: python-dotenv>=1.1.1
Requires-Dist: python-jose>=3.5.0
Requires-Dist: python-multipart>=0.0.20
Requires-Dist: redis>=7.1.0
Requires-Dist: requests>=2.32.5
Requires-Dist: restrictedpython>=8.0
Requires-Dist: rich>=13.0.0
Requires-Dist: sqlalchemy>=2.0.44
Requires-Dist: typer>=0.12.0
Requires-Dist: uvicorn>=0.38.0
Requires-Dist: websockets>=15.0.1
